{
  "queues": [
    {
      "name": "foo",
      "raw_name": "jwdk_foo",
      "visibility_timeout": 30,
      "delay_seconds": 3,
      "maximum_message_size": 204800,
      "message_retention_period": 345600,
      "dead_letter_target": "foo_dead_letter",
      "max_receive_count": "2"
    },
    {
      "name": "foo_dead_letter",
      "raw_name": "jwdk_foo",
      "visibility_timeout": 30,
      "delay_seconds": 0,
      "maximum_message_size": 204800,
      "message_retention_period": 345600,
      "dead_letter_target": "",
      "max_receive_count": "100"
    }
  ]
}
